dplus_ceres.cp311-win_amd64.pyd
dplus_ceres/call_cost_function.pyx
dplus_ceres/dplus_ceres.pyx
dplus_ceres/iteration_callback_func.pyx
dplus_ceres-0.6.0.dist-info/LICENSE
dplus_ceres-0.6.0.dist-info/METADATA
dplus_ceres-0.6.0.dist-info/WHEEL
dplus_ceres-0.6.0.dist-info/top_level.txt
dplus_ceres-0.6.0.dist-info/RECORD
