Metadata-Version: 2.1
Name: dplus-ceres
Version: 0.6.0
Summary: A Python wrapper of Ceres 2.0 - for DPlus
Home-page: http://www.researchsoftware.co.il
Author: Devora Witty
Author-email: devora@researchsoftware.co.il
License: pyceres:
Platform: UNKNOWN
Classifier: Development Status :: 4 - Beta
Classifier: Environment :: Console
Classifier: Intended Audience :: Science/Research
Classifier: License :: OSI Approved :: BSD License
Classifier: Operating System :: OS Independent
Classifier: Programming Language :: Python
Classifier: Programming Language :: Python :: 3.9
Classifier: Programming Language :: Python :: 3.10
Classifier: Programming Language :: Python :: 3.11
Classifier: Programming Language :: Python :: 3.12
Requires-Python: >=3.9
License-File: LICENSE
Requires-Dist: numpy >=1.23.0
